Workbook
Name blend_efb_pct: INPUTS!$B$9
Name blend_opdc_pct: INPUTS!$B$10
Name ffb_tph: INPUTS!$B$4
Name op_hours: INPUTS!$B$5
Name op_days: INPUTS!$B$6
Name pksa_dose: INPUTS!$B$17
Name grow_days: INPUTS!$B$30
Name bsf_area: INPUTS!$B$29
Name cert_tier: INPUTS!$B$33
Name bsf_density: INPUTS!$B$28
Name soil_type: INPUTS!$B$34

Sheet INPUTS
A1: CFI MASTER CALCULATOR — INPUT PARAMETERS
A2: All yellow cells are user-editable. Changes propagate to all tabs.
A3: MILL PARAMETERS
A4: FFB Throughput (TPH) | B4: 60 | C4: tonnes per hour Fresh Fruit Bunch
A5: Operating Hours / Day | B5: 20 | C5: hours
A6: Operating Days / Month | B6: 25 | C6: days
A7: FFB tonnes/day (calculated) | B7: =IFERROR(INPUTS!$B$4*INPUTS!$B$5,0) | C7: t/day
A8: BLEND COMPOSITION (must sum to 100%)
A9: EFB % | B9: 60 | C9: %
A10: OPDC % | B10: 40 | C10: %
A11: Residue 3 % | B11: 0 | C11: % | E11: (select from dropdown)
A12: Residue 4 % | B12: 0 | C12: % | E12: (select from dropdown)
A13: Residue 5 % | B13: 0 | C13: % | E13: (select from dropdown)
A14: Blend Total (must = 100%) | B14: =IFERROR(SUM($B$9:$B$13),0) | C14: =IF(B14=100,"OK","ERROR: blend must = 100%")
A15: STAGE 2 — CHEMICAL TREATMENT
A16: Chemical Selection | B16: PKSA
A17: PKSA Dose (kg/t substrate) | B17: 8 | C17: kg/t
A18: Chemical Cost ($/t substrate) | B18: =IFERROR(VLOOKUP($B$16,S2_Chemical_Library!$A$3:$H$20,5,FALSE),0) | C18: $/t
A19: STAGE 3 — BIOLOGICAL TREATMENT
A20: Consortium Selection | B20: Best 5 (Provibio + EM4)
A21: Organism 1 | B21: Lactobacillus spp.
A22: Organism 2 | B22: Saccharomyces cerevisiae
A23: Organism 3 | B23: Bacillus subtilis
A24: Organism 4 | B24: Bacillus amyloliquefaciens
A25: Organism 5 | B25: Trichoderma harzianum
A26: Bio Treatment Days (min 5) | B26: 5
A27: STAGE 4 — BSF REARING
A28: Inoculation Density (neonates/m2) | B28: 5000
A29: BSF Rearing Area (m2) | B29: 1000
A30: Grow-out Days (6-18) | B30: 12
A31: Neonate Cost ($/1000 neonates) | B31: 0.01
A32: CERTIFICATION & SOIL TARGET
A33: Certification Tier | B33: None
A34: Target Soil Type | B34: All

Sheet S0_Waste_Streams
A1: STAGE 0 — WASTE STREAM MASS BALANCE
A3: Waste Stream | B3: Yield (% FFB) | C3: t/hr | D3: t/day | E3: t/month | F3: DM% | G3: DM t/month
A4: EFB | B4: 0.23 | C4: =IFERROR(INPUTS!$B$4*B4,0) | D4: =IFERROR(C4*INPUTS!$B$5,0) | E4: =IFERROR(D4*INPUTS!$B$6,0) | F4: 0.375 | G4: =IFERROR(E4*F4,0)
A5: OPDC | B5: 0.05 | C5: =IFERROR(INPUTS!$B$4*B5,0) | D5: =IFERROR(C5*INPUTS!$B$5,0) | E5: =IFERROR(D5*INPUTS!$B$6,0) | F5: 0.3 | G5: =IFERROR(E5*F5,0)
A6: PKSA | B6: 0.008 | C6: =IFERROR(INPUTS!$B$4*B6,0) | D6: =IFERROR(C6*INPUTS!$B$5,0) | E6: =IFERROR(D6*INPUTS!$B$6,0) | F6: 0.98 | G6: =IFERROR(E6*F6,0)
A7: PMF | B7: 0.13 | C7: =IFERROR(INPUTS!$B$4*B7,0) | D7: =IFERROR(C7*INPUTS!$B$5,0) | E7: =IFERROR(D7*INPUTS!$B$6,0) | F7: 0.6 | G7: =IFERROR(E7*F7,0)
A8: POME | B8: 0.67 | C8: =IFERROR(INPUTS!$B$4*B8,0) | D8: =IFERROR(C8*INPUTS!$B$5,0) | E8: =IFERROR(D8*INPUTS!$B$6,0) | F8: 0.04 | G8: =IFERROR(E8*F8,0)
A9: PKS | B9: 0.055 | C9: =IFERROR(INPUTS!$B$4*B9,0) | D9: =IFERROR(C9*INPUTS!$B$5,0) | E9: =IFERROR(D9*INPUTS!$B$6,0) | F9: 0.85 | G9: =IFERROR(E9*F9,0)
A11: BLEND MASS BALANCE
A12: EFB in Blend (t/month) | B12: =IFERROR(E4*INPUTS!$B$9/100,0)
A13: OPDC in Blend (t/month) | B13: =IFERROR(E5*INPUTS!$B$10/100,0)
A14: Total Blend Substrate (t/month) | B14: =IFERROR(B12+B13,0)
A15: Total Blend Substrate (t/day) | B15: =IFERROR(B14/INPUTS!$B$6,0)

Sheet S0_Lab_Analysis
A1: STAGE 0 — FULL LAB ANALYSIS MATRIX (DM BASIS)
A3: Parameter | B3: EFB | C3: OPDC | D3: PKSA | E3: PMF | F3: POME | G3: PKS | H3: PPF | I3: Trunk | J3: Frond | K3: Sludge | L3: 60:40 Blend
A4: DM% | B4: 37.5 | C4: 30 | D4: 98 | E4: 60 | F4: 4 | G4: 85 | H4: 55 | I4: 25 | J4: 35 | K4: 25 | L4: =IFERROR(B4*INPUTS!$B$9/100+C4*INPUTS!$B$10/100,0)
A5: Moisture% | B5: 62.5 | C5: 70 | D5: 2 | E5: 40 | F5: 96 | G5: 15 | H5: 45 | I5: 75 | J5: 65 | K5: 75 | L5: =IFERROR(B5*INPUTS!$B$9/100+C5*INPUTS!$B$10/100,0)
A6: pH | B6: 6.5 | C6: 6.8 | D6: 11.2 | E6: 5.5 | F6: 4.5 | G6: 6 | H6: 5.8 | I6: 5.5 | J6: 5.6 | K6: 7 | L6: =IFERROR(B6*INPUTS!$B$9/100+C6*INPUTS!$B$10/100,0)
A7: N% | B7: 0.85 | C7: 2.45 | D7: 0.5 | E7: 0.75 | F7: 0.6 | G7: 0.4 | H7: 0.55 | I7: 0.3 | J7: 1.2 | K7: 2.8 | L7: =IFERROR(B7*INPUTS!$B$9/100+C7*INPUTS!$B$10/100,0)
A8: P% | B8: 0.34 | C8: 0.43 | D8: 2.94 | E8: 0.1 | F8: 0.25 | G8: 0.05 | H8: 0.08 | I8: 0.03 | J8: 0.12 | K8: 1.5 | L8: =IFERROR(B8*INPUTS!$B$9/100+C8*INPUTS!$B$10/100,0)
A9: K% | B9: 2.2 | C9: 2.2 | D9: 12.5 | E9: 1.8 | F9: 1.5 | G9: 0.3 | H9: 1.4 | I9: 0.8 | J9: 1.5 | K9: 0.5 | L9: =IFERROR(B9*INPUTS!$B$9/100+C9*INPUTS!$B$10/100,0)
A10: Ca% | B10: 0.2 | C10: 1 | D10: 8.5 | E10: 0.35 | F10: 0.3 | G10: 0.1 | H10: 0.25 | I10: 0.15 | J10: 0.4 | K10: 1.2 | L10: =IFERROR(B10*INPUTS!$B$9/100+C10*INPUTS!$B$10/100,0)
A11: Mg% | B11: 0.21 | C11: 0.55 | D11: 2.2 | E11: 0.15 | F11: 0.2 | G11: 0.05 | H11: 0.12 | I11: 0.08 | J11: 0.18 | K11: 0.35 | L11: =IFERROR(B11*INPUTS!$B$9/100+C11*INPUTS!$B$10/100,0)
A12: S% | B12: 0.12 | C12: 0.18 | D12: 0.3 | E12: DATA_GAP | F12: DATA_GAP | G12: DATA_GAP | H12: DATA_GAP | I12: DATA_GAP | J12: DATA_GAP | K12: DATA_GAP | L12: =IFERROR(B12*INPUTS!$B$9/100+C12*INPUTS!$B$10/100,0)
A13: Fe_ppm | B13: 1200 | C13: 800 | D13: 5000 | E13: DATA_GAP | F13: DATA_GAP | G13: DATA_GAP | H13: DATA_GAP | I13: DATA_GAP | J13: DATA_GAP | K13: DATA_GAP | L13: =IFERROR(B13*INPUTS!$B$9/100+C13*INPUTS!$B$10/100,0)
A14: Zn_ppm | B14: 25 | C14: 45 | D14: 60 | E14: DATA_GAP | F14: DATA_GAP | G14: DATA_GAP | H14: DATA_GAP | I14: DATA_GAP | J14: DATA_GAP | K14: DATA_GAP | L14: =IFERROR(B14*INPUTS!$B$9/100+C14*INPUTS!$B$10/100,0)
A15: Cu_ppm | B15: 8 | C15: 15 | D15: 30 | E15: DATA_GAP | F15: DATA_GAP | G15: DATA_GAP | H15: DATA_GAP | I15: DATA_GAP | J15: DATA_GAP | K15: DATA_GAP | L15: =IFERROR(B15*INPUTS!$B$9/100+C15*INPUTS!$B$10/100,0)
A16: Mn_ppm | B16: 50 | C16: 80 | D16: 200 | E16: DATA_GAP | F16: DATA_GAP | G16: DATA_GAP | H16: DATA_GAP | I16: DATA_GAP | J16: DATA_GAP | K16: DATA_GAP | L16: =IFERROR(B16*INPUTS!$B$9/100+C16*INPUTS!$B$10/100,0)
A17: B_ppm | B17: 12 | C17: 8 | D17: 20 | E17: DATA_GAP | F17: DATA_GAP | G17: DATA_GAP | H17: DATA_GAP | I17: DATA_GAP | J17: DATA_GAP | K17: DATA_GAP | L17: =IFERROR(B17*INPUTS!$B$9/100+C17*INPUTS!$B$10/100,0)
A18: OM% | B18: 95 | C18: 83.5 | D18: 0 | E18: 92 | F18: 70 | G18: 96 | H18: 90 | I18: 88 | J18: 85 | K18: 60 | L18: =IFERROR(B18*INPUTS!$B$9/100+C18*INPUTS!$B$10/100,0)
A19: Ash% | B19: 5 | C19: 16.5 | D19: 100 | E19: 8 | F19: 30 | G19: 4 | H19: 10 | I19: 12 | J19: 15 | K19: 40 | L19: =IFERROR(B19*INPUTS!$B$9/100+C19*INPUTS!$B$10/100,0)
A20: Lignin% | B20: 22 | C20: 30.7 | D20: 0 | E20: 27 | F20: 0 | G20: 50 | H20: 24 | I20: 18 | J20: 20 | K20: 5 | L20: =IFERROR(B20*INPUTS!$B$9/100+C20*INPUTS!$B$10/100,0)
A21: Cellulose% | B21: 35 | C21: 22 | D21: 0 | E21: 33 | F21: 0 | G21: 30 | H21: 32 | I21: 40 | J21: 38 | K21: 8 | L21: =IFERROR(B21*INPUTS!$B$9/100+C21*INPUTS!$B$10/100,0)
A22: C_N_ratio | B22: 60 | C22: 20 | D22: 0 | E22: 55 | F22: 12 | G22: 100 | H22: 65 | I22: 80 | J22: 40 | K22: 10 | L22: =IFERROR(B22*INPUTS!$B$9/100+C22*INPUTS!$B$10/100,0)
A24: AS-RECEIVED BASIS (multiply DM-basis values by DM%/100)
A25: (N, P, K, Ca, Mg as-received shown below)
A26: N% (AR) | B26: =IFERROR(B7*B4/100,0) | C26: =IFERROR(C7*C4/100,0) | D26: =IFERROR(D7*D4/100,0) | E26: =IFERROR(E7*E4/100,0) | F26: =IFERROR(F7*F4/100,0) | G26: =IFERROR(G7*G4/100,0) | H26: =IFERROR(H7*H4/100,0) | I26: =IFERROR(I7*I4/100,0) | ... K26: =IFERROR(K7*K4/100,0)
A27: P% (AR) | B27: =IFERROR(B8*B4/100,0) | C27: =IFERROR(C8*C4/100,0) | D27: =IFERROR(D8*D4/100,0) | E27: =IFERROR(E8*E4/100,0) | F27: =IFERROR(F8*F4/100,0) | G27: =IFERROR(G8*G4/100,0) | H27: =IFERROR(H8*H4/100,0) | I27: =IFERROR(I8*I4/100,0) | ... K27: =IFERROR(K8*K4/100,0)
A28: K% (AR) | B28: =IFERROR(B9*B4/100,0) | C28: =IFERROR(C9*C4/100,0) | D28: =IFERROR(D9*D4/100,0) | E28: =IFERROR(E9*E4/100,0) | F28: =IFERROR(F9*F4/100,0) | G28: =IFERROR(G9*G4/100,0) | H28: =IFERROR(H9*H4/100,0) | I28: =IFERROR(I9*I4/100,0) | ... K28: =IFERROR(K9*K4/100,0)
A29: Ca% (AR) | B29: =IFERROR(B10*B4/100,0) | C29: =IFERROR(C10*C4/100,0) | D29: =IFERROR(D10*D4/100,0) | E29: =IFERROR(E10*E4/100,0) | F29: =IFERROR(F10*F4/100,0) | G29: =IFERROR(G10*G4/100,0) | H29: =IFERROR(H10*H4/100,0) | I29: =IFERROR(I10*I4/100,0) | ... K29: =IFERROR(K10*K4/100,0)
A30: Mg% (AR) | B30: =IFERROR(B11*B4/100,0) | C30: =IFERROR(C11*C4/100,0) | D30: =IFERROR(D11*D4/100,0) | E30: =IFERROR(E11*E4/100,0) | F30: =IFERROR(F11*F4/100,0) | G30: =IFERROR(G11*G4/100,0) | H30: =IFERROR(H11*H4/100,0) | I30: =IFERROR(I11*I4/100,0) | ... K30: =IFERROR(K11*K4/100,0)

Sheet S1_Preprocessing
A1: STAGE 1 — MECHANICAL PREPROCESSING
A3: MECHANICAL SIZE REDUCTION
A4: Step 1: Shredding (EFB) | B4: 50-100mm | C4: mm | D4: Primary size reduction
A5: Step 2: Hammer Mill | B5: 2mm | C5: mm | D5: Target particle size for BSF substrate
A6: Target Particle Size | B6: 2 | C6: mm | D6: Optimal for microbial access and BSF feeding
A7: Moisture Loss from Processing | B7: 3 | C7: % | D7: Mechanical compression moisture loss
A9: MASS BALANCE — PREPROCESSING
A10: Substrate Input (t/month) | B10: =IFERROR(S0_Waste_Streams!B13,0)
A11: Moisture Loss (t/month) | B11: =IFERROR(B10*0.03,0)
A12: Substrate After Preprocessing (t/month) | B12: =IFERROR(B10-B11,0)
A14: PKSA SOAKING
A15: PKSA Dose (from INPUTS) | B15: =INPUTS!$B$17 | C15: kg/t
A16: PKSA Required (t/month) | B16: =IFERROR(B12*B15/1000,0)
A17: PKSA Cost ($/month) | B17: 0
A18: Water for PKSA Soaking (litres/month) | B18: =IFERROR(B16*1000*5,0) | D18: Ratio: 5L water per kg PKSA
A20: MIXING PARAMETERS
A21: Mixing Duration (minutes) | B21: 60-90 | C21: min
A22: Expected pH After PKSA Contact | B22: 10-12 | C22: pH
A23: Mixing Method | B23: Mechanical paddle mixer
A25: ENERGY CONSUMPTION
A26: Shredder (kWh/t) | B26: 25
A27: Hammer Mill (kWh/t) | B27: 35
A28: Mixer (kWh/t) | B28: 8
A29: Total Energy (kWh/t substrate) | B29: =IFERROR(SUM(B26:B28),0)
A30: Total Energy Cost ($/month @ $0.08/kWh) | B30: =IFERROR(B29*B12*0.08,0)
A32: STAGE 1 COST SUMMARY
A33: Energy Cost ($/month) | B33: =B30
A34: PKSA Cost ($/month) | B34: 0
A35: Total Stage 1 Cost ($/month) | B35: =IFERROR(B33+B34,0)
A36: Cost per Tonne Substrate ($/t) | B36: =IFERROR(B35/B12,0)

Sheet S1_Lab_Analysis
A1: STAGE 1 — POST-PREPROCESSING LAB PARAMETERS
A3: Parameter | B3: Pre-Processing | C3: Post-Processing | D3: Notes
A4: Particle Size (mm) | B4: Variable | C4: 2 | D4: Target: 2mm via hammer mill
A5: pH | B5: =IFERROR(S0_Lab_Analysis!L6,0) | C5: 11 | D5: Post PKSA contact: 10-12
A6: Moisture% | B6: =IFERROR(S0_Lab_Analysis!L5,0) | C6: =IFERROR(B6-3,0) | D6: ~3% loss from mechanical processing
A7: DM% | B7: =IFERROR(S0_Lab_Analysis!L4,0) | C7: =IFERROR(100-C6,0) | D7: Inverse of moisture
A8: Lignin% | B8: =IFERROR(S0_Lab_Analysis!L20,0) | C8: =B8 | D8: Unchanged at Stage 1
A9: Cellulose% | B9: =IFERROR(S0_Lab_Analysis!L21,0) | C9: =B9 | D9: Unchanged at Stage 1
A10: C:N ratio | B10: =IFERROR(S0_Lab_Analysis!L22,0) | C10: =B10 | D10: Unchanged at Stage 1
A11: N% | B11: =IFERROR(S0_Lab_Analysis!L7,0) | C11: =B11 | D11: Unchanged at Stage 1
A12: P% | B12: =IFERROR(S0_Lab_Analysis!L8,0) | C12: =B12 | D12: May increase slightly from PKSA P contribution
A13: K% | B13: =IFERROR(S0_Lab_Analysis!L9,0) | C13: =B13 | D13: May increase from PKSA K contribution

Sheet S2_Chemical_Treatment
A1: STAGE 2 — CHEMICAL PRE-TREATMENT
A3: CHEMICAL SELECTION (from INPUTS)
A4: Selected Chemical | B4: =INPUTS!$B$16
A5: Dose Rate (kg/t) | B5: =INPUTS!$B$17
A6: Cost ($/t substrate) | B6: =IFERROR(VLOOKUP(B4,S2_Chemical_Library!$A$3:$H$20,5,FALSE),0)
A7: Lignin Reduction (%) | B7: =IFERROR(VLOOKUP(B4,S2_Chemical_Library!$A$3:$H$20,7,FALSE),0)
A8: Chemical Alert Status | B8: =IF(B4="NaOH","WARNING: CAUSTIC - SEE ALERT","OK")
A9: WARNING ROW | B9: =IF(B4="NaOH","ALERT: NaOH selected. Caustic soda requires full PPE (gloves, goggles, face shield). Risk of substrate over-alkalisation above pH 13. Neutralise fully before BSF inoculation. PKSA is the safer zero-cost alternative.","")
A11: pH TRAJECTORY
A12: Substrate pH (pre-treatment) | B12: =IFERROR(S1_Lab_Analysis!C5,6.5) | D12: From S1 Lab Analysis
A13: pH After Chemical Contact (0hr) | B13: 10-12 | D13: Immediate alkalinity from PKSA
A14: pH at 8-12hr (1st turning) | B14: 9-11 | D14: CO2 carbonation begins
A15: pH at 16-20hr (2nd turning) | B15: 8-9 | D15: Further neutralisation
A16: pH at 24hr (final) | B16: 6.5-8.0 | D16: Target: ready for biologicals
A18: NEUTRALISATION TIMELINE (24hr — MANDATORY)
A19: T=0hr: Chemical applied + mixing | B19: 60-90 min mixing | C19: HARD-CODED
A20: T=8-12hr: FIRST TURNING | B20: Mandatory physical turning | C20: HARD-CODED
A21: T=16-20hr: SECOND TURNING | B21: Mandatory physical turning | C21: HARD-CODED
A22: T=24hr: Neutralisation complete | B22: Check pH 6.5-8.0 | C22: HARD-CODED
A24: SUBSTRATE PARAMETERS POST-CHEMICAL TREATMENT
A25: Lignin% (post-treatment) | B25: =IFERROR(S1_Lab_Analysis!C9*(1-B7),0)
A26: pH (post-neutralisation) | B26: 6.5-8.0
A27: Moisture% | B27: =IFERROR(S1_Lab_Analysis!C6,65)
A28: C:N ratio | B28: =IFERROR(S1_Lab_Analysis!C10,32)
A30: STAGE 2 COST CALCULATION
A31: Substrate Volume (t/month) | B31: =IFERROR(S1_Preprocessing!B12,0)
A32: Chemical Cost per Tonne ($/t) | B32: =B6
A33: Total Chemical Cost ($/month) | B33: =IFERROR(B31*B32,0)

Sheet S2_Chemical_Library
A1: STAGE 2 — CHEMICAL LIBRARY (FULL REFERENCE)
A3: Chemical | B3: Function | C3: Dose Min (kg/t) | D3: Dose Max (kg/t) | E3: Cost ($/t substrate) | F3: pH Effect | G3: Lignin Reduction | H3: BSF Compatible | I3: Notes
A4: PKSA | B4: Alkalinity / liming | C4: 6 | D4: 10 | E4: 0 | F4: 10-12 | G4: 0.325 | H4: Y | I4: Mill by-product. ZERO cost at mill gate (Guardrail 3).
A5: CaCO3 | B5: pH buffer | C5: 5 | D5: 15 | E5: 1.05 | F5: 7.5-8.5 | G5: 0.075 | H5: Y | I5: Mild buffer, food-grade available.
A6: H2O2 | B6: Oxidative delignification | C6: 2 | D6: 5 | E6: 3.5 | F6: neutral | G6: 0.175 | H6: Y | I6: Requires dosing control.
A7: Urea | B7: N supplement / pH adjustment | C7: 3 | D7: 8 | E7: 0.9 | F7: +0.5-1.0 | G7: 0 | H7: Y | I7: Raises pH slightly via ammonia.
A8: Lime Ca(OH)2 | B8: Alkalinity | C8: 5 | D8: 20 | E8: 0.8 | F8: 11-13 | G8: 0.25 | H8: Y | I8: Agricultural lime, widely available.
A9: MgSO4 | B9: Mg supplement | C9: 1 | D9: 3 | E9: 1.2 | F9: neutral | G9: 0 | H9: Y | I9: Epsom salt, foliar grade.
A10: NPK 15-15-15 | B10: Nutrient balance | C10: 2 | D10: 5 | E10: 4.5 | F10: slight drop | G10: 0 | H10: Y | I10: Compound fertiliser.
A11: Molasses | B11: Carbon source / BSF attractant | C11: 5 | D11: 20 | E11: 6 | F11: drop | G11: 0 | H11: Y | I11: Sugarcane by-product.
A12: PKSA+CaCO3 | B12: Combined buffer | C12: 11 | D12: 11 | E12: 1.05 | F12: 9-11 | G12: 0.275 | H12: Y | I12: PKSA 6 + CaCO3 5 kg/t.
A13: PKSA+H2O2+Urea | B13: Best overall treatment | C13: 16 | D13: 16 | E13: 6.4 | F13: 10-12 | G13: 0.375 | H13: Y | I13: PKSA 8 + H2O2 3 + Urea 5 kg/t.
A14: NaOH | B14: Strong alkalinity | C14: 2 | D14: 10 | E14: 0.4 | F14: 12-14 | G14: 0.3 | H14: Y | I14: CAUSTIC. Full PPE required. See Guardrail 2.

Sheet S3_Biological_Treatment
A1: STAGE 3 — BIOLOGICAL PRE-TREATMENT
A3: CONSORTIUM RECIPE (from INPUTS)
A4: Organism 1 | B4: =INPUTS!$B$21 | C4: =IFERROR(VLOOKUP(B4,S3_Biological_Library!$A$3:$J$20,5,FALSE),"") | D4: =IFERROR(VLOOKUP(B4,S3_Biological_Library!$A$3:$J$20,3,FALSE),"")
A5: Organism 2 | B5: =INPUTS!$B$22 | C5: =IFERROR(VLOOKUP(B5,S3_Biological_Library!$A$3:$J$20,5,FALSE),"") | D5: =IFERROR(VLOOKUP(B5,S3_Biological_Library!$A$3:$J$20,3,FALSE),"")
A6: Organism 3 | B6: =INPUTS!$B$23 | C6: =IFERROR(VLOOKUP(B6,S3_Biological_Library!$A$3:$J$20,5,FALSE),"") | D6: =IFERROR(VLOOKUP(B6,S3_Biological_Library!$A$3:$J$20,3,FALSE),"")
A7: Organism 4 | B7: =INPUTS!$B$24 | C7: =IFERROR(VLOOKUP(B7,S3_Biological_Library!$A$3:$J$20,5,FALSE),"") | D7: =IFERROR(VLOOKUP(B7,S3_Biological_Library!$A$3:$J$20,3,FALSE),"")
A8: Organism 5 | B8: =INPUTS!$B$25 | C8: =IFERROR(VLOOKUP(B8,S3_Biological_Library!$A$3:$J$20,5,FALSE),"") | D8: =IFERROR(VLOOKUP(B8,S3_Biological_Library!$A$3:$J$20,3,FALSE),"")
A10: CONSORTIUM WAVE SCHEDULE
A11: WAVE 1 — Apply at Day 0 | B11: All Wave 1 organisms applied simultaneously | D11: Concurrent-safe: Lacto, Saccharo, B.subtilis, B.amylo, Trichoderma
A12: WAVE 2 — Apply at Day 3 | B12: After initial pH drop from Wave 1 fermentation | D12: Aspergillus niger, Pleurotus, Phanerochaete
A13: WAIT — Minimum 5 days total bio-treatment | B13: MANDATORY biological safety rule | D13: BSF inoculation NOT before Day 5
A15: 5-DAY BIOLOGICAL TREATMENT RULE (GUARDRAIL 6)
A16: Bio Treatment Days (from INPUTS) | B16: =IFERROR(INPUTS!$B$26,5)
A17: Minimum Required Days | B17: 5
A18: BSF INOCULATION STATUS | B18: =IF(B16>=5,"READY - BSF inoculation permitted","NOT READY - Minimum 5 days required")
A20: PREDICTED IMPROVEMENTS FROM BIOLOGICALS
A21: Further Lignin Reduction (%) | B21: 10-15% | D21: Additional to Stage 2 chemical reduction
A22: C:N Improvement | B22: Target 15-25 | D22: Optimal range for BSF feeding
A23: Protein Enrichment | B23: +5-8% from microbial biomass
A25: BSF YIELD UPLIFT FROM CONSORTIUM
A26: Consortium Configuration | B26: =INPUTS!$B$20
A27: Uplift Factor | B27: =IF(B26="None",1.0,IF(B26="Wave 1 Only",1.15,IF(OR(B26="Wave 1 + Wave 2",B26="Best 5 (Provibio + EM4)"),1.15,1.15)))
A28: Effective BSF FW Yield Multiplier | B28: =B27
A30: STAGE 3 COST CALCULATION
A31: Total Biological Cost ($/t substrate) | B31: 5.4
A32: Substrate Volume (t/month) | B32: =IFERROR(S1_Preprocessing!B12,0)
A33: Total Bio Cost ($/month) | B33: =IFERROR(B31*B32,0)

Sheet S3_Biological_Library
A1: STAGE 3 — BIOLOGICAL LIBRARY (FULL REFERENCE)
A3: Organism | B3: Strain | C3: Function | D3: Application Rate | E3: Wave | F3: Consortium | G3: Target Substrate | H3: BSF Uplift % | I3: Cost ($/t) | J3: Source
A4: Lactobacillus spp. | B4: EM4-LAB01 | C4: Primary fermentation, pH reduction, pathogen suppression | D4: 10 mL/kg substrate | E4: WAVE1 | F4: Y | G4: Sugars, simple carbohydrates | H4: 3 | I4: 0.8 | J4: EM4
A5: Saccharomyces cerevisiae | B5: EM4-SC01 | C5: Yeast fermentation, ethanol production, nutrient release | D5: 5 mL/kg substrate | E5: WAVE1 | F5: Y | G5: Sugars, starches | H5: 2 | I5: 0.6 | J5: EM4
A6: Bacillus subtilis | B6: PV-BS01 | C6: Cellulase production, protein enrichment, pathogen suppression | D6: 5 g/kg substrate | E6: WAVE1 | F6: Y | G6: Cellulose, hemicellulose | H6: 4 | I6: 1.2 | J6: Provibio
A7: Bacillus amyloliquefaciens | B7: PV-BA01 | C7: Amylase, protease production, nutrient mineralisation | D7: 5 g/kg substrate | E7: WAVE1 | F7: Y | G7: Starch, protein complexes | H7: 3.5 | I7: 1.3 | J7: Provibio
A8: Trichoderma harzianum | B8: PV-TH01 | C8: Cellulase / ligninase, bio-control, substrate conditioning | D8: 8 g/kg substrate | E8: WAVE1 | F8: Y | G8: Cellulose, lignin | H8: 4.5 | I8: 1.5 | J8: Provibio
A9: Aspergillus niger | B9: PV-AN01 | C9: Phosphate solubilisation, citric acid production | D9: 5 g/kg substrate | E9: WAVE2 | F9: Y | G9: Phosphate minerals, cellulose | H9: 2.5 | I9: 1.1 | J9: Provibio
A10: Pleurotus ostreatus | B10: PV-PO01 | C10: White-rot lignin degradation, laccase production | D10: 10 g/kg substrate | E10: WAVE2 | F10: Y | G10: Lignin, aromatic compounds | H10: 3 | I10: 2 | J10: Provibio
A11: Phanerochaete chrysosporium | B11: PV-PC01 | C11: White-rot, high lignin peroxidase activity | D11: 8 g/kg substrate | E11: WAVE2 | F11: Y | G11: Recalcitrant lignin | H11: 3.5 | I11: 2.5 | J11: Provibio
A12: Bacillus thuringiensis | B12: PV-BT01 | C12: Insecticidal protein (Cry toxins), pest bio-control | D12: 5 g/kg substrate | E12: CAUTION | F12: CAUTION | G12: Lepidoptera, some Diptera larvae | H12: 0 | I12: 1.8 | J12: Provibio
A13: Beauveria bassiana | B13: PV-BB01 | C13: Entomopathogenic fungus, pest bio-control | D13: 5 g/kg substrate | E13: CAUTION | F13: CAUTION | G13: Broad-spectrum insect pathogen | H13: 0 | I13: 2.2 | J13: Provibio
A14: Rhodopseudomonas palustris | B14: EM4-RP01 | C14: Photosynthetic N fixation, organic acid metabolism | D14: 10 mL/kg substrate | E14: WAVE1 | F14: Y | G14: Organic acids, N-fixation | H14: 2 | I14: 0.9 | J14: EM4
A15: Actinomycetes spp. | B15: EM4-AC01 | C15: Chitin degradation, antibiotic production, humus formation | D15: 5 mL/kg substrate | E15: WAVE1 | F15: Y | G15: Chitin, complex organics | H15: 1.5 | I15: 0.7 | J15: EM4

Sheet S4_BSF_Rearing
A1: STAGE 4 — BSF REARING & GROW-OUT
A3: INOCULATION PARAMETERS
A4: Inoculation Density (neonates/m2) | B4: =INPUTS!$B$28 | C4: neonates/m2
A5: Rearing Area (m2) | B5: =INPUTS!$B$29 | C5: m2
A6: Total Neonates Required | B6: =IFERROR(B4*B5,0) | C6: neonates
A7: Neonate Cost ($/1000) | B7: =INPUTS!$B$31 | C7: $
A8: Total Neonate Cost ($/batch) | B8: =IFERROR(B6*B7/1000,0) | C8: $
A10: ENVIRONMENTAL PARAMETERS (from BSF research)
A11: Temperature Optimal | B11: 27-30 | C11: C | D11: Stop below 20C, above 40C
A12: Relative Humidity | B12: 60-70 | C12: %RH | D12: Larval rearing tray humidity
A13: Substrate pH | B13: 6.5-7.0 | C13: pH | D13: Range: 6.0-7.5
A14: Light Regime | B14: No direct sunlight. Exclude UV. 12hr dark cycle.
A15: Substrate C:N Optimal | B15: 15-25 | D15: Post-treatment target
A16: Substrate Moisture | B16: 60-70 | C16: % | D16: Active feeding moisture
A18: BSF YIELD CALCULATIONS
A19: Grow-out Days (from INPUTS) | B19: =INPUTS!$B$30
A20: Day 6 Baseline Yield (kg FW / t substrate) | B20: 70
A21: Day 18 Maximum Yield (kg FW / t substrate) | B21: 140
A22: BSF FW Yield (kg/t substrate) — BASELINE | B22: =IFERROR(B20+(B19-6)/12*(B21-B20),0)
A23: Consortium Uplift Factor | B23: =IFERROR(S3_Biological_Treatment!B28,1.0)
A24: BSF FW Yield (kg/t substrate) — WITH UPLIFT | B24: =IFERROR(B22*B23,0)
A26: MONTHLY PRODUCTION
A27: Substrate Processed (t/month) | B27: =IFERROR(S1_Preprocessing!B12,0)
A28: BSF Fresh Weight (t/month) | B28: =IFERROR(B27*B24/1000,0)
A29: BSF Dry Matter (t/month) @ 35% DM | B29: =IFERROR(B28*0.35,0)
A30: Crude Fat in DM (t/month) @ 23% | B30: =IFERROR(B29*0.23,0)
A31: Extractable Oil (t/month) @ 85% press efficiency | B31: =IFERROR(B30*0.85,0)
A32: Defatted Meal (t/month) | B32: =IFERROR(B29-B30,0)
A33: Chitin in DM (t/month) @ 9.3% | B33: =IFERROR(B29*0.09300000000000001,0)
A34: Frass/Residue Mass (t/month) | B34: =IFERROR(B27*(1-B24*1.15/1000),0)

Sheet S4_BSF_Lab
A1: STAGE 4 — BSF PRE-PUPAE COMPOSITION
A3: FRESH WEIGHT (FW) BASIS — from CFI Lab Analysis
A4: Parameter | B4: Value | C4: Unit | D4: Source
A5: Moisture | B5: 65 | C5: % | D5: CFI Lab Analysis
A6: Dry Matter | B6: 35 | C6: % | D6: CFI Lab Analysis
A7: Crude Protein (FW) | B7: 36 | C7: % FW | D7: CFI Lab Analysis
A8: Fat / Crude Lipid (FW) | B8: 8 | C8: % FW | D8: CFI Lab Analysis
A9: Chitin (FW) | B9: 3.3 | C9: % FW | D9: CFI Lab Analysis
A10: Ash (FW) | B10: 3.5 | C10: % FW | D10: CFI Lab Analysis
A12: DEFATTED MEAL COMPOSITION (DM BASIS)
A13: Crude Protein (defatted) | B13: 51 | C13: % DM | D13: CFI Lab Analysis
A14: Chitin | B14: 9.3 | C14: % DM | D14: CFI Lab Analysis
A15: Ash | B15: 10 | C15: % DM | D15: CFI Lab Analysis
A17: AMINO ACID PROFILE (reference)
A18: Methionine | B18: 2.1 | C18: % CP
A19: Lysine | B19: 6.6 | C19: % CP
A20: Threonine | B20: 3.7 | C20: % CP
A21: Leucine | B21: 7.2 | C21: % CP

Sheet S5A_Frass_Pathway
A1: STAGE 5A — FRASS / COMPOST PATHWAY
A3: FRASS MASS BALANCE
A4: Substrate Input (t/month) | B4: =IFERROR(S4_BSF_Rearing!B27,0)
A5: BSF FW Yield (kg/t substrate) | B5: =IFERROR(S4_BSF_Rearing!B24,0)
A6: Frass Mass (t/month) | B6: =IFERROR(B4*(1000-B5*1.15)/1000,0)
A8: FRASS COMPOSITION (from research data)
A9: N% | B9: 2.5 | D9: Enriched from BSF metabolism
A10: P% | B10: 1.8 | D10: Concentrated via larval processing
A11: K% | B11: 2 | D11: Retained from substrate
A12: OM% | B12: 65 | D12: Post-bioconversion organic matter
A13: pH | B13: 7 | D13: Near neutral
A14: Moisture% | B14: 35 | D14: Post-screening moisture
A15: C:N ratio | B15: 12 | D15: Excellent for soil application
A17: FERTILISER VALUE — NPK vs SYNTHETIC EQUIVALENT
A18: Frass N content (t N/month) | B18: =IFERROR(B6*2.5/100,0)
A19: Frass P content (t P/month) | B19: =IFERROR(B6*1.8/100,0)
A20: Frass K content (t K/month) | B20: =IFERROR(B6*2.0/100,0)
A22: SOIL TYPE ADJUSTED APPLICATION
A23: Target Soil (from INPUTS) | B23: =INPUTS!$B$34
A24: Recommended Application Rate | B24: 5-10 t/ha/yr | D24: Varies by soil type and palm age
A26: FRASS PRODUCT VALUE
A27: Frass Price ($/t) | B27: 80
A28: Frass Revenue ($/month) | B28: =IFERROR(B6*B27,0)

Sheet S5B_BSF_Extraction
A1: STAGE 5B — BSF LARVAL EXTRACTION
A3: LARVAE SEPARATION
A4: BSF Fresh Weight (t/month) | B4: =IFERROR(S4_BSF_Rearing!B28,0) | D4: From Stage 4
A5: Separation Method | B5: Mechanical sieving + thermal | D5: Industry standard
A6: Separation Efficiency | B6: 95% | D6: Fresh larvae recovery
A7: Recovered Larvae (t/month) | B7: =IFERROR(B4*0.95,0) | D7: Post-separation
A9: OIL EXTRACTION
A10: BSF DM (t/month) | B10: =IFERROR(S4_BSF_Rearing!B29,0)
A11: Crude Fat in DM (t/month) | B11: =IFERROR(S4_BSF_Rearing!B30,0)
A12: Oil Press Efficiency | B12: 85%
A13: Extracted Oil (t/month) | B13: =IFERROR(S4_BSF_Rearing!B31,0)
A14: Oil Residue / Press Cake (t/month) | B14: =IFERROR(B11-B13,0)
A16: DEFATTED MEAL
A17: Defatted Meal (t/month) | B17: =IFERROR(S4_BSF_Rearing!B32,0)
A18: Crude Protein in Meal (%) | B18: 51
A20: CHITIN RECOVERY (OPTIONAL)
A21: Chitin in DM (t/month) | B21: =IFERROR(S4_BSF_Rearing!B33,0)
A22: Chitin Recovery Feasible | B22: Optional — requires chemical deproteination | D22: Flag: not included in base-case revenue
A24: STAGE 5B PROCESSING COSTS
A25: Drying Cost ($/t FW larvae) | B25: 25
A26: Oil Pressing Cost ($/t DM) | B26: 40
A27: Separation Cost ($/t FW) | B27: 15
A28: Packaging / Storage ($/t product) | B28: 20
A29: Total Processing Cost ($/month) | B29: =IFERROR(B25*S4_BSF_Rearing!B28+B26*S4_BSF_Rearing!B29+B27*S4_BSF_Rearing!B28+B28*(S4_BSF_Rearing!B32+S4_BSF_Rearing!B31),0)

Sheet S6_Product_Valuation
A1: STAGE 6 — PRODUCT VALUATION BY CERTIFICATION TIER
A2: Selected Certification Tier: | B2: =INPUTS!$B$33
A4: INSECT MEAL VALUATION
A5: Product | B5: Mass (t/month) | C5: Price ($/t) | D5: Revenue ($/month) | E5: Notes
A6: Defatted Insect Meal | B6: =IFERROR(S5B_BSF_Extraction!B17,0) | C6: =IF(INPUTS!$B$33="None",1200,IF(INPUTS!$B$33="FSSC 22000",3500,IF(INPUTS!$B$33="ISO 22716",4500,1200))) | D6: =IFERROR(B6*C6,0) | E6: Guardrail 4: verified price ranges
A7: Price Range: None | C7: $1200/t
A8: Price Range: FSSC 22000 | C8: $3500-5000/t
A9: Price Range: ISO 22716 Premium | C9: $4500-6500/t
A11: INSECT OIL VALUATION
A12: Product | B12: Mass (t/month) | C12: Price ($/t) | D12: Revenue ($/month) | E12: Notes
A13: Insect Oil | B13: =IFERROR(S5B_BSF_Extraction!B13,0) | C13: =IF(INPUTS!$B$33="None",900,IF(INPUTS!$B$33="FSSC 22000",3500,IF(INPUTS!$B$33="ISO 22716",9000,900))) | D13: =IFERROR(B13*C13,0)
A14: Feed grade (None) | C14: $900-1200/t
A15: FSSC 22000 | C15: $3500-6000/t
A16: ISO 22716 (Pharma lipid) | C16: $9000-18000/t | E16: FSSC/ISO unlocks 3-9x oil uplift
A18: FRASS FERTILISER VALUATION
A19: Frass Fertiliser | B19: =IFERROR(S5A_Frass_Pathway!B6,0) | C19: 80 | D19: =IFERROR(B19*C19,0)
A21: CHITIN VALUATION (OPTIONAL)
A22: Chitin (if extracted) | B22: =IFERROR(S4_BSF_Rearing!B33,0) | C22: 15000 | D22: =IFERROR(B22*C22,0) | E22: Range: $15,000-25,000/t
A24: TOTAL REVENUE SUMMARY
A25: Total Monthly Revenue (excl. chitin) | B25: =IFERROR(D6+D13+D19,0)
A26: Total Monthly Revenue (incl. chitin) | B26: =IFERROR(B25+D22,0)
A27: Total Annual Revenue (excl. chitin) | B27: =IFERROR(B25*12,0)

Sheet Summary_Dashboard
A1: CFI BIOCONVERSION — EXECUTIVE SUMMARY DASHBOARD
A3: KEY INPUTS
A4: FFB Mill Capacity | B4: =INPUTS!$B$4 | C4: TPH
A5: Blend Ratio (EFB:OPDC) | B5: =INPUTS!$B$9&":"&INPUTS!$B$10
A6: BSF Grow Days | B6: =INPUTS!$B$30 | C6: days
A7: Certification Tier | B7: =INPUTS!$B$33
A8: Rearing Area | B8: =INPUTS!$B$29 | C8: m2
A10: MONTHLY PRODUCTION
A11: Total Substrate Processed | B11: =IFERROR(S1_Preprocessing!B12,0) | C11: t/month
A12: BSF Fresh Weight | B12: =IFERROR(S4_BSF_Rearing!B28,0) | C12: t/month
A13: BSF Dry Matter | B13: =IFERROR(S4_BSF_Rearing!B29,0) | C13: t/month
A14: Insect Meal (defatted) | B14: =IFERROR(S4_BSF_Rearing!B32,0) | C14: t/month
A15: Insect Oil | B15: =IFERROR(S4_BSF_Rearing!B31,0) | C15: t/month
A16: Frass / Compost | B16: =IFERROR(S5A_Frass_Pathway!B6,0) | C16: t/month
A17: Chitin (optional) | B17: =IFERROR(S4_BSF_Rearing!B33,0) | C17: t/month
A19: REVENUE SUMMARY
A20: Revenue Stream | B20: Monthly ($) | C20: Annual ($) | D20: % of Total
A21: Insect Meal | B21: =IFERROR(S6_Product_Valuation!D6,0) | C21: =IFERROR(B21*12,0) | D21: =IFERROR(B21/B24,0)
A22: Insect Oil | B22: =IFERROR(S6_Product_Valuation!D13,0) | C22: =IFERROR(B22*12,0) | D22: =IFERROR(B22/B24,0)
A23: Frass Fertiliser | B23: =IFERROR(S6_Product_Valuation!D19,0) | C23: =IFERROR(B23*12,0) | D23: =IFERROR(B23/B24,0)
A24: TOTAL REVENUE | B24: =IFERROR(SUM(B21:B23),0) | C24: =IFERROR(B24*12,0) | D24: 100%
A26: COST BREAKDOWN BY STAGE
A27: Stage 1: Preprocessing | B27: =IFERROR(S1_Preprocessing!B35,0) | C27: =IFERROR(B27*12,0)
A28: Stage 2: Chemical Treatment | B28: =IFERROR(S2_Chemical_Treatment!B33,0) | C28: =IFERROR(B28*12,0)
A29: Stage 3: Biological Treatment | B29: =IFERROR(S3_Biological_Treatment!B33,0) | C29: =IFERROR(B29*12,0)
A30: Stage 4: BSF Neonates | B30: =IFERROR(S4_BSF_Rearing!B8,0) | C30: =IFERROR(B30*12,0)
A31: Stage 5B: Processing | B31: =IFERROR(S5B_BSF_Extraction!B29,0) | C31: =IFERROR(B31*12,0)
A32: TOTAL COSTS | B32: =IFERROR(SUM(B27:B31),0) | C32: =IFERROR(B32*12,0)
A34: PROFITABILITY
A35: Gross Profit ($/month) | B35: =IFERROR(B24-B32,0)
A36: Gross Margin (%) | B36: =IFERROR(B35/B24,0)
A37: Revenue per Tonne Substrate ($/t) | B37: =IFERROR(B24/B11,0)
A39: CERTIFICATION UPLIFT COMPARISON
A40: Metric | B40: None | C40: FSSC 22000 | D40: ISO 22716
A41: Meal Price ($/t) | B41: 1200 | C41: 3500 | D41: 4500
A42: Oil Price ($/t) | B42: 900 | C42: 3500 | D42: 9000
A43: Meal Revenue ($/month) | B43: =IFERROR(S4_BSF_Rearing!$B$32*B41,0) | C43: =IFERROR(S4_BSF_Rearing!$B$32*C41,0) | D43: =IFERROR(S4_BSF_Rearing!$B$32*D41,0)
A44: Oil Revenue ($/month) | B44: =IFERROR(S4_BSF_Rearing!$B$31*B42,0) | C44: =IFERROR(S4_BSF_Rearing!$B$31*C42,0) | D44: =IFERROR(S4_BSF_Rearing!$B$31*D42,0)
A45: Total Revenue ($/month) | B45: =IFERROR(B43+B44+S6_Product_Valuation!D19,0) | C45: =IFERROR(C43+C44+S6_Product_Valuation!D19,0) | D45: =IFERROR(D43+D44+S6_Product_Valuation!D19,0)

Sheet Soil_Fertiliser_Matrix
A1: INDONESIAN SOIL TYPES & FERTILISER MATRIX
A3: SOIL TYPE PARAMETERS
A4: Soil Type | B4: Coverage% | C4: pH | D4: CEC | E4: Base Sat% | F4: N (g/kg) | G4: P (mg/kg) | H4: K (cmol/kg) | I4: Yield Factor | J4: Notes
A5: Inceptisols | B5: 39 | C5: 4.1 | D5: 15.4 | E5: 45 | F5: 2.7 | G5: 124 | H5: 0.25 | I5: 1 | J5: Best fertility, standard reference
A6: Ultisols | B6: 24 | C6: 4.5 | D6: 8.2 | E6: 22 | F6: 1.8 | G6: 65 | H6: 0.15 | I6: 1 | J6: Standard NPK baseline for fertiliser calcs
A7: Oxisols | B7: 8 | C7: 4.4 | D7: 5.5 | E7: 15 | F7: 1.5 | G7: 40 | H7: 0.1 | I7: 0.85 | J7: Fe/Al oxide-dominant, low CEC, high P fixation
A8: Histosols | B8: 7 | C8: 3.8 | D8: 45 | E8: 10 | F8: 15 | G8: 200 | H8: 0.08 | I8: 0.9 | J8: Peat/organic, C=24.5%, very high OM
A9: Spodosols | B9: 22 | C9: 4.77 | D9: 4 | E9: 12 | F9: 1 | G9: 30 | H9: 0.08 | I9: 0.69 | J9: Sandy, lowest fertility, ~31% lower yield vs Ultisols
A11: NPK REQUIREMENTS BY PALM AGE BRACKET (kg/ha/yr — Ultisol baseline)
A12: Age Bracket | B12: N (kg/ha/yr) | C12: P (kg/ha/yr) | D12: K (kg/ha/yr)
A13: Young 1-3yr | B13: 80 | C13: 35 | D13: 60
A14: Immature 4-6yr | B14: 120 | C14: 50 | D14: 100
A15: Mature 7-15yr | B15: 150 | C15: 60 | D15: 180
A16: Old 16+yr | B16: 130 | C16: 55 | D16: 150
A18: CFI FRASS + PKSA SUBSTITUTION BY SOIL TYPE
A19: Soil Type | B19: N Reduction% | C19: P Reduction% | D19: Frass Rate (t/ha) | E19: PKSA Rate (t/ha) | F19: Synthetic Cost Saved ($/ha/yr)
A20: Inceptisols | B20: 40 | C20: 50 | D20: 5 | E20: 2 | F20: 82.8
A21: Ultisols | B21: 0 | C21: 0 | D21: 10 | E21: 1 | F21: 124.8
A22: Oxisols | B22: 0 | C22: 0 | D22: 10 | E22: 2 | F22: 124.8
A23: Histosols | B23: 80 | C23: 70 | D23: 5 | E23: 2 | F23: 51.6
A24: Spodosols | B24: 0 | C24: 0 | D24: 10 | E24: 1 | F24: 124.8
A26: PKSA AGRONOMIC VALUE
A27: PKSA Synthetic Replacement Value | B27: 129.82 | C27: $/t | D27: At $0 mill-gate cost (Guardrail 3)

Sheet CAPEX_OPEX
A1: CAPEX & OPEX ANALYSIS
A3: CAPITAL EXPENDITURE (CAPEX)
A4: Equipment / Item | B4: Estimated Cost (USD) | C4: Category
A5: Stage 1 — Shredder (EFB) | B5: 85000 | C5: Stage 1
A6: Stage 1 — Hammer mill | B6: 45000 | C6: Stage 1
A7: Stage 1 — Mixing tank + conveyor | B7: 35000 | C7: Stage 1
A8: Stage 1 — PKSA soaking vessel | B8: 15000 | C8: Stage 1
A9: Stage 2 — Chemical dosing system | B9: 20000 | C9: Stage 2
A10: Stage 2 — Neutralisation tank | B10: 25000 | C10: Stage 2
A11: Stage 3 — Biological inoculation system | B11: 18000 | C11: Stage 3
A12: Stage 3 — Composting area (covered) | B12: 40000 | C12: Stage 3
A13: Stage 4 — BSF rearing shed (per 500m2) | B13: 60000 | C13: Stage 4
A14: Stage 4 — BSF neonate nursery | B14: 25000 | C14: Stage 4
A15: Stage 4 — Climate control system | B15: 35000 | C15: Stage 4
A16: Stage 5A — Frass screening/bagging | B16: 20000 | C16: Stage 5A
... A22: Laboratory — Basic QC lab | B22: 35000 | C22: Laboratory
A23: TOTAL CAPEX | B23: =IFERROR(SUM(B5:B22),0)
A25: MONTHLY OPERATING EXPENDITURE (OPEX)
A26: Cost Item | B26: Monthly Cost (USD) | C26: Notes
A27: Chemical Treatment | B27: =IFERROR(S2_Chemical_Treatment!B33,0) | C27: From Stage 2
A28: Biological Treatment | B28: =IFERROR(S3_Biological_Treatment!B33,0) | C28: From Stage 3
A29: BSF Neonates | B29: =IFERROR(S4_BSF_Rearing!B8,0) | C29: From Stage 4
A30: Processing (S5B) | B30: =IFERROR(S5B_BSF_Extraction!B29,0) | C30: From Stage 5B
A31: Energy / Utilities | B31: =IFERROR(S1_Preprocessing!B30,0) | C31: From Stage 1
A32: Labour (estimated) | B32: 8000 | C32: 10 workers @ $800/month
A33: Maintenance (2% CAPEX/month) | B33: =IFERROR(B23*0.02/12,0) | C33: Industry standard
A34: Quality Control / Lab | B34: 2000 | C34: Monthly QC testing
A35: Transport / Logistics | B35: 3000 | C35: Product distribution
A36: TOTAL MONTHLY OPEX | B36: =IFERROR(SUM(B27:B35),0)
A38: PAYBACK & NPV ANALYSIS
A39: Total CAPEX | B39: =B23
A40: Monthly Gross Profit | B40: =IFERROR(Summary_Dashboard!B24-B36,0)
A41: Payback Period (months) | B41: =IFERROR(B39/B40,0)
A42: Payback Period (years) | B42: =IFERROR(B41/12,0)
A44: IRR Discount Rate (user-adjustable) | B44: 0.12
A45: Annual Net Cash Flow | B45: =IFERROR(B40*12,0)
A46: 5-Year NPV (simple estimate) | B46: =IFERROR(B45/(1+B44)^1+B45/(1+B44)^2+B45/(1+B44)^3+B45/(1+B44)^4+B45/(1+B44)^5-B39,0)
